<?xml version='1.0' encoding='utf-8'?>
<annotation>
  <folder>classification_results</folder>
  <filename>17_20250628_posterior_classification.png</filename>
  <path>F:\projek dosen\prototype riset\hotspot-analyzer\data\SPECT\NBL\17\17_20250628_posterior_classification.png</path>
  <source>
    <database>Hotspot Classification Results</database>
  </source>
  <size>
    <width>256</width>
    <height>1024</height>
    <depth>1</depth>
  </size>
  <segmented>0</segmented>
  <object>
    <name>Abnormal</name>
    <pose>Unspecified</pose>
    <truncated>0</truncated>
    <difficult>0</difficult>
    <bndbox>
      <xmin>111</xmin>
      <ymin>314</ymin>
      <xmax>139</xmax>
      <ymax>342</ymax>
    </bndbox>
    <!-- Classification data: {"segment": "thoracic vertebrae", "probability_normal": 0.007854282855987549, "probability_abnormal": 0.9921457171440125, "hotspot_pixels": 586, "hotspot_mm2": 3368.612474204623} -->
  </object>
</annotation>